pytracts/__init__.py
pytracts/_local_iso8601.py
pytracts/exceptions.py
pytracts/message_types.py
pytracts/messages.py
pytracts/query.py
pytracts/to_dict.py
pytracts/to_json.py
pytracts/to_url.py
pytracts/util.py
pytracts/flask/__init__.py
pytracts/webapp2/__init__.py
tests/__init__.py
tests/message_types_test.py
tests/messages_test.py
tests/test_util.py
tests/to_dict_test.py
tests/to_json_test.py
tests/to_url_test.py
tests/util_test.py
pytracts-2.0.0.dist-info/LICENSE
pytracts-2.0.0.dist-info/METADATA
pytracts-2.0.0.dist-info/WHEEL
pytracts-2.0.0.dist-info/entry_points.txt
pytracts-2.0.0.dist-info/top_level.txt
pytracts-2.0.0.dist-info/RECORD
