Metadata-Version: 2.1
Name: pytracts
Version: 2.0.0
Summary: Library to define data contracts for JSON and build RESTful services with Webapp2 or Flask
Home-page: https://github.com/rmorlok/pytracts
Author: Ryan Morlok
Author-email: ryan.morlok@morlok.com
License: Apache 2.0
Project-URL: Documentation, https://github.com/rmorlok/pytracts
Project-URL: Source, https://github.com/rmorlok/pytracts
Project-URL: Tracker, https://github.com/rmorlok/pytracts/issues
Keywords: protocol json contract
Classifier: Intended Audience :: Developers
Classifier: License :: OSI Approved :: Apache Software License
Classifier: Operating System :: MacOS :: MacOS X
Classifier: Operating System :: Microsoft :: Windows
Classifier: Operating System :: POSIX :: Linux
Classifier: Programming Language :: Python :: 2.7
Classifier: Topic :: Software Development :: Libraries
Classifier: Topic :: Software Development :: Libraries :: Python Modules
Requires-Python: !=3.0.*,!=3.1.*,>=2.7
License-File: LICENSE
Requires-Dist: six
Provides-Extra: all
Requires-Dist: pytest (>=6.2.2) ; extra == 'all'
Requires-Dist: pycodestyle ; extra == 'all'
Requires-Dist: pytest-cov ; extra == 'all'
Provides-Extra: test
Requires-Dist: pytest (>=6.2.2) ; extra == 'test'
Requires-Dist: pycodestyle ; extra == 'test'
Requires-Dist: pytest-cov ; extra == 'test'
